MANIFEST.in
README.rst
setup.py
docs/HISTORY.txt
docs/LICENSE.GPL
docs/LICENSE.txt
plonetheme/__init__.py
plonetheme.onegovbear.egg-info/PKG-INFO
plonetheme.onegovbear.egg-info/SOURCES.txt
plonetheme.onegovbear.egg-info/dependency_links.txt
plonetheme.onegovbear.egg-info/entry_points.txt
plonetheme.onegovbear.egg-info/namespace_packages.txt
plonetheme.onegovbear.egg-info/not-zip-safe
plonetheme.onegovbear.egg-info/requires.txt
plonetheme.onegovbear.egg-info/top_level.txt
plonetheme/onegovbear/__init__.py
plonetheme/onegovbear/configure.zcml
plonetheme/onegovbear/interfaces.py
plonetheme/onegovbear/lawgiver.zcml
plonetheme/onegovbear/permissions.zcml
plonetheme/onegovbear/resources.zcml
plonetheme/onegovbear/rolemap.xml
plonetheme/onegovbear/testing.py
plonetheme/onegovbear/browser/__init__.py
plonetheme/onegovbear/browser/configure.zcml
plonetheme/onegovbear/browser/dynamic_scss_resources.py
plonetheme/onegovbear/browser/forms.py
plonetheme/onegovbear/browser/z3cjbot/Products.TinyMCE.skins.tinymce.plugins.plonebrowser.plonebrowser.htm.pt
plonetheme/onegovbear/browser/z3cjbot/Products.TinyMCE.skins.tinymce.plugins.table.table.htm.pt
plonetheme/onegovbear/browser/z3cjbot/Products.TinyMCE.skins.tinymce.themes.advanced.skins.plone.dialog.css.dtml
plonetheme/onegovbear/locales/plone.tinymce-manual.pot
plonetheme/onegovbear/locales/plonetheme.onegovbear-manual.pot
plonetheme/onegovbear/locales/plonetheme.onegovbear.pot
plonetheme/onegovbear/locales/de/LC_MESSAGES/plone.tinymce.po
plonetheme/onegovbear/locales/de/LC_MESSAGES/plonetheme.onegovbear.po
plonetheme/onegovbear/locales/en/LC_MESSAGES/plonetheme.onegovbear.po
plonetheme/onegovbear/locales/fr/LC_MESSAGES/plonetheme.onegovbear.po
plonetheme/onegovbear/locales/it/LC_MESSAGES/plonetheme.onegovbear.po
plonetheme/onegovbear/profiles/default/actions.xml
plonetheme/onegovbear/profiles/default/browserlayer.xml
plonetheme/onegovbear/profiles/default/cssregistry.xml
plonetheme/onegovbear/profiles/default/metadata.xml
plonetheme/onegovbear/profiles/default/theme.xml
plonetheme/onegovbear/profiles/default/tinymce.xml
plonetheme/onegovbear/tests/__init__.py
plonetheme/onegovbear/tests/test_custom_scss_variables.py
plonetheme/onegovbear/tests/test_installation.py
plonetheme/onegovbear/theme/index.html
plonetheme/onegovbear/theme/manifest.cfg
plonetheme/onegovbear/theme/rules.xml
