Metadata-Version: 1.1
Name: plonetheme.onegovbear
Version: 1.3.4
Summary: OneGov Plone theme sponsored by the city of Bern.
Home-page: https://github.com/OneGov/plonetheme.onegovbear
Author: 4teamwork AG
Author-email: mailto:info@4teamwork.ch
License: GPL2
Keywords: plone theme onegov
Platform: UNKNOWN
Classifier: Environment :: Web Environment
Classifier: Framework :: Plone
Classifier: Framework :: Plone :: 4.3
Classifier: License :: OSI Approved :: GNU General Public License (GPL)
Classifier: Operating System :: OS Independent
Classifier: Programming Language :: Python
